redditwrap.py
redditwrap-0.1.0.dist-info/WHEEL
redditwrap-0.1.0.dist-info/METADATA
redditwrap-0.1.0.dist-info/RECORD
